stgfunc/__init__.py
stgfunc/_metadata.py
stgfunc/experimental.py
stgfunc/other.py
stgfunc/py.typed
stgfunc-3.1.1.dist-info/LICENSE
stgfunc-3.1.1.dist-info/METADATA
stgfunc-3.1.1.dist-info/WHEEL
stgfunc-3.1.1.dist-info/top_level.txt
stgfunc-3.1.1.dist-info/RECORD
