Metadata-Version: 2.1
Name: stgfunc
Version: 3.1.1
Summary: VapourSynth functions and utils
Author: Setsugen no ao
Author-email: setsugen@setsugen.dev
Maintainer: Setsugen no ao
Maintainer-email: setsugen@setsugen.dev
Project-URL: Source Code, https://github.com/Setsugennoao/stgfunc
Project-URL: Documentation, https://stgfunc.setsugen.dev/en/latest/
Project-URL: Contact, http://fansub.setsugen.dev/discord
Classifier: Programming Language :: Python :: 3
Classifier: License :: OSI Approved :: MIT License
Classifier: Operating System :: OS Independent
Requires-Python: >=3.12
License-File: LICENSE
Requires-Dist: VapourSynth >=68
Requires-Dist: vstools >=3.2.0
